.gitignore
CHANGES.rst
LICENSE
MANIFEST.in
README.rst
irodscollector.ini
run_tests.py
setup.py
src/eudat/__init__.py
src/eudat.accounting.client.egg-info/PKG-INFO
src/eudat.accounting.client.egg-info/SOURCES.txt
src/eudat.accounting.client.egg-info/dependency_links.txt
src/eudat.accounting.client.egg-info/entry_points.txt
src/eudat.accounting.client.egg-info/namespace_packages.txt
src/eudat.accounting.client.egg-info/not-zip-safe
src/eudat.accounting.client.egg-info/requires.txt
src/eudat.accounting.client.egg-info/top_level.txt
src/eudat/accounting/__init__.py
src/eudat/accounting/client/__init__.py
src/eudat/accounting/client/__main__.py
src/eudat/accounting/client/iRODScollector.py
src/eudat/accounting/client/utils.py