Metadata-Version: 1.1
Name: eudat.accounting.client
Version: 1.0.1
Summary: Upload accounting records to an eudat accounting server
Home-page: https://github.com/raphael-ritz/eudat.accounting.client
Author: Raphael Ritz
Author-email: raphael.ritz@gmail.com
License: BSD
Keywords: EUDAT,storage,accounting,comamndline,client
Platform: UNKNOWN
Classifier: Environment :: Console
Classifier: Intended Audience :: System Administrators
Classifier: Programming Language :: Python :: 2.7
Classifier: Operating System :: OS Independent
Classifier: License :: OSI Approved :: BSD License
Classifier: Topic :: Utilities
